langchain_ktgendm/LICENSE
langchain_ktgendm/README.md
langchain_ktgendm/__init__.py
langchain_ktgendm/ktgendm.py
langchain_ktgendm-0.0.9.dist-info/METADATA
langchain_ktgendm-0.0.9.dist-info/WHEEL
langchain_ktgendm-0.0.9.dist-info/top_level.txt
langchain_ktgendm-0.0.9.dist-info/RECORD
