Metadata-Version: 2.1
Name: langchain_ktgendm
Version: 0.0.9
Summary: langchain_ktgendm
Author: langchain_ktgendm
Author-email: 
Requires-Python: >=3.8
